nullpy/__init__.py
nullpy/core.py
nullpy-0.0.2.dist-info/METADATA
nullpy-0.0.2.dist-info/WHEEL
nullpy-0.0.2.dist-info/top_level.txt
nullpy-0.0.2.dist-info/RECORD
