Metadata-Version: 2.4
Name: nullpy
Version: 0.0.2
Summary: Automated data cleaning tool
Author-email: Foresty <dsparthsrivastava@email.com>
Project-URL: Homepage, https://github.com/Parth-Srivastava-bithub/nullpy
Requires-Python: >=3.8
Requires-Dist: numpy
Requires-Dist: pandas
Requires-Dist: scikit-learn
Requires-Dist: scipy
Requires-Dist: rich
